corpusly/__init__.py
corpusly-0.0.1.dist-info/LICENSE
corpusly-0.0.1.dist-info/METADATA
corpusly-0.0.1.dist-info/WHEEL
corpusly-0.0.1.dist-info/top_level.txt
corpusly-0.0.1.dist-info/RECORD
